setup.cfg
setup.py
datetimeutc/__init__.py
datetimeutc/utils.py
datetimeutc.egg-info/PKG-INFO
datetimeutc.egg-info/SOURCES.txt
datetimeutc.egg-info/dependency_links.txt
datetimeutc.egg-info/requires.txt
datetimeutc.egg-info/top_level.txt