Metadata-Version: 1.0
Name: datetimeutc
Version: 0.1.1
Summary: Because why are we dealing with timezones?
Home-page: http://github.com/whosken/datetimeutc
Author: Ken Hu
Author-email: whosbacon@gmail.com
License: MIT
Keywords: datetime,timezone,utc
Platform: UNKNOWN
